boned_html/__init__.py
boned_html/boner.py
boned_html/chunker.py
boned_html/exceptions.py
boned_html/tests.py
boned_html/version.py
boned_html-0.2.dist-info/DESCRIPTION.rst
boned_html-0.2.dist-info/METADATA
boned_html-0.2.dist-info/RECORD
boned_html-0.2.dist-info/WHEEL
boned_html-0.2.dist-info/metadata.json
boned_html-0.2.dist-info/top_level.txt
