Metadata-Version: 2.0
Name: boned-html
Version: 0.2
Summary: A small library to smartly extract text from html and eventually rebuild html
Home-page: https://github.com/jurismarches/boned-html
Author: Jurismarches
Author-email: contact@jurismarches.com
License: UNKNOWN
Keywords: html,lxml,scrapping
Platform: UNKNOWN
Classifier: Development Status :: 4 - Beta
Classifier: License :: OSI Approved :: MIT License
Classifier: Intended Audience :: Developers
Classifier: Programming Language :: Python
Classifier: Programming Language :: Python :: 3.4
Classifier: Programming Language :: Python :: 3.5
Classifier: Programming Language :: Python :: 3.6
Requires-Dist: lxml
Provides-Extra: quality
Requires-Dist: flake8 (>=2.5.4); extra == 'quality'
Provides-Extra: test
Requires-Dist: coverage (>=4.0.3); extra == 'test'
Requires-Dist: nose (>=1.3.7); extra == 'test'
